oslc4py_domains_auto/AutomationPlan.py
oslc4py_domains_auto/AutomationRequest.py
oslc4py_domains_auto/AutomationResult.py
oslc4py_domains_auto/Contribution.py
oslc4py_domains_auto/ParameterDefinition.py
oslc4py_domains_auto/ParameterInstance.py
oslc4py_domains_auto/__init__.py
oslc4py_domains_auto/oslc_constants.py
oslc4py_domains_auto-0.1.2.dist-info/LICENCE
oslc4py_domains_auto-0.1.2.dist-info/METADATA
oslc4py_domains_auto-0.1.2.dist-info/WHEEL
oslc4py_domains_auto-0.1.2.dist-info/top_level.txt
oslc4py_domains_auto-0.1.2.dist-info/RECORD
