Metadata-Version: 2.1
Name: oslc4py-domains-auto
Version: 0.1.2
Summary: OSLC automation domain package
Home-page: https://pajda.fit.vutbr.cz/verifit/oslc4py-domains-auto
Author: Matej Grós
Author-email: 492906@mail.muni.cz
License: UNKNOWN
Platform: UNKNOWN
Classifier: Programming Language :: Python :: 3
Classifier: License :: OSI Approved :: Eclipse Public License 2.0 (EPL-2.0)
Classifier: Operating System :: OS Independent
Requires-Python: >=3.6
License-File: LICENCE
Requires-Dist: oslc4py-client>=0.1.2
